xshl/target/__about__.py
xshl/target/__init__.py
xshl_target-0.3.2.data/data/COPYRIGHT
xshl_target-0.3.2.data/data/LICENSE
xshl_target-0.3.2.dist-info/LICENSE
xshl_target-0.3.2.dist-info/METADATA
xshl_target-0.3.2.dist-info/WHEEL
xshl_target-0.3.2.dist-info/top_level.txt
xshl_target-0.3.2.dist-info/RECORD
