Metadata-Version: 2.1
Name: xshl-target
Version: 0.3.2
Summary: Python Library for XSHL Target
Home-page: https://github.com/mcode-cc/py-xshl-target
Author: MCode GmbH
Author-email: python@xshl.org
License: GPLv3
Project-URL: Bug Tracker, https://github.com/mcode-cc/py-xshl-target/issues
Project-URL: Source Code, https://github.com/mcode-cc/py-xshl-target
Keywords: link tree target digraph reference groot wind unwind
Platform: Any
Classifier: License :: OSI Approved :: GNU General Public License v3 (GPLv3)
Classifier: Development Status :: 1 - Planning
Classifier: Environment :: No Input/Output (Daemon)
Classifier: Environment :: Console
Classifier: Intended Audience :: Developers
Classifier: Operating System :: OS Independent
Classifier: Programming Language :: Python :: 3.7
Classifier: Programming Language :: Python :: 3.8
Classifier: Programming Language :: Python :: 3.9
Classifier: Programming Language :: Python :: 3 :: Only
Classifier: Programming Language :: Python :: Implementation :: CPython
Classifier: Programming Language :: Python :: Implementation :: PyPy
Classifier: Topic :: Internet
Classifier: Topic :: Communications
Classifier: Topic :: Database
Classifier: Topic :: Software Development :: Libraries
Classifier: Topic :: Software Development :: Libraries :: Python Modules
Classifier: Topic :: Software Development :: Libraries :: Application Frameworks
Classifier: Topic :: System :: Networking
Requires-Python: >=3.8
License-File: LICENSE
Requires-Dist: networkx (>=2.8.5)
Provides-Extra: default
Requires-Dist: numpy (>=1.20) ; extra == 'default'
Requires-Dist: scipy (>=1.8) ; extra == 'default'
Requires-Dist: matplotlib (>=3.4) ; extra == 'default'
Requires-Dist: pandas (>=1.3) ; extra == 'default'
